actionista/__init__.py
actionista/binary_operators.py
actionista/date_utils.py
actionista/todoist/__init__.py
actionista/todoist/action_cli.py
actionista/todoist/action_commands.py
actionista/todoist/adhoc_cli.py
actionista/todoist/config.py
actionista/todoist/config_cli.py
actionista/todoist/rest_api.py
actionista/todoist/tasks_utils.py
actionista/todoist/todoist_cli.py
actionista/todoist/utils.py
actionista_todoist-2019.9.16.dist-info/LICENSE
actionista_todoist-2019.9.16.dist-info/METADATA
actionista_todoist-2019.9.16.dist-info/WHEEL
actionista_todoist-2019.9.16.dist-info/entry_points.txt
actionista_todoist-2019.9.16.dist-info/top_level.txt
actionista_todoist-2019.9.16.dist-info/RECORD
