Metadata-Version: 2.1
Name: actionista-todoist
Version: 2019.9.16
Summary: Actionista Action CLI for Todoist. Add, select, print, reschedule, modify, and complete tasks in a batch-wise fashion from the command line.
Home-page: https://github.com/scholer/actionista-todoist
Author: Rasmus Scholer Sorensen
Author-email: rasmusscholer@gmail.com
License: GNU General Public License v3 (GPLv3)
Keywords: Todoist,Tasks,Productivity,TODO,GTD,CLI
Platform: UNKNOWN
Classifier: Development Status :: 4 - Beta
Classifier: Intended Audience :: End Users/Desktop
Classifier: License :: OSI Approved :: GNU General Public License v3 (GPLv3)
Classifier: Programming Language :: Python :: 3
Classifier: Programming Language :: Python :: 3.5
Classifier: Programming Language :: Python :: 3.6
Classifier: Operating System :: MacOS
Classifier: Operating System :: Microsoft
Classifier: Operating System :: POSIX :: Linux
Requires-Python: >=3.6
Requires-Dist: todoist-python (>=8.0)
Requires-Dist: pyyaml
Requires-Dist: pytz
Requires-Dist: python-dateutil
Requires-Dist: dateparser
Requires-Dist: parsedatetime
Requires-Dist: click
